{
  "ticker": "GEX",
  "models": {
    "PRICE_DOWN_15_MA20": {
      "target": "fwd_positive_t180",
      "accuracy": 0.5199,
      "auc": 0.7514,
      "top_features": {
        "nearest_support": "0.2715468",
        "bb_lower": "0.12468492",
        "vol_60d": "0.041218378",
        "fib_786_level": "0.03440862",
        "swing_high_252": "0.02830662",
        "ema_100": "0.027643206",
        "sma_200": "0.025250593",
        "adv_20": "0.024644932",
        "sma_100": "0.021356927",
        "ema_10": "0.018843258",
        "ema_5": "0.01779399",
        "senkou_span_b": "0.016852846",
        "stoch_rsi_oversold": "0.01651026",
        "sma_10": "0.016448325",
        "sma_50": "0.013607877",
        "swing_low_252": "0.012662029",
        "ema_50": "0.012656012",
        "open_fvg_above": "0.012206344",
        "atr_14": "0.011871646",
        "ema_200": "0.010363258"
      }
    },
    "RSI_OVERSOLD": {
      "target": "fwd_positive_t60",
      "accuracy": 0.5954,
      "auc": 0.5272,
      "top_features": {
        "ema_50": "0.1210294",
        "fib_ext_1272": "0.05797216",
        "sma_50": "0.045450836",
        "ema_5": "0.043959863",
        "ma20_deviation_pct": "0.033860274",
        "cloud_bullish": "0.03074705",
        "swing_high_252": "0.030270942",
        "dist_to_52w_low_pct": "0.027931513",
        "nearest_support": "0.02453594",
        "fib_ext_1618": "0.024120616",
        "sma_5": "0.018768635",
        "rsi_divergence_bullish": "0.016208643",
        "ema_200": "0.015304541",
        "vwap": "0.015217199",
        "return_60d": "0.014190807",
        "alligator_jaw": "0.013971299",
        "chikou_span": "0.013283425",
        "sma_100": "0.012972507",
        "uptrend_quality_score": "0.012062655",
        "breadth_pct_above_50sma": "0.011692885"
      }
    },
    "PRICE_DOWN_15_20D": {
      "target": "fwd_positive_t5",
      "accuracy": 0.5304,
      "auc": 0.5513,
      "top_features": {
        "vol_explosion_streak": "0.03424502",
        "sma_100": "0.019730475",
        "fib_786_level": "0.019343905",
        "price_below_cloud": "0.018383428",
        "bos_bullish": "0.017430926",
        "price_above_cloud": "0.01671771",
        "ema_10": "0.016446149",
        "rsi_divergence_bearish": "0.015136562",
        "hit_ceiling": "0.014655505",
        "sma_5": "0.013862016",
        "swing_high_252": "0.013782987",
        "dmi_crossover_bullish": "0.013582139",
        "decline_20d_flag": "0.013562363",
        "rsi_divergence_bullish": "0.01333579",
        "fib_ext_1618": "0.012680294",
        "tenkan_sen": "0.01218742",
        "fib_618_level": "0.011513983",
        "fib_382_level": "0.010935394",
        "uptrend_duration": "0.010333726",
        "open_fvg_below": "0.009950911"
      }
    },
    "DMI_WAVE": {
      "target": "fwd_positive_t10",
      "accuracy": 0.5283,
      "auc": 0.5401,
      "top_features": {
        "three_pushes_high_flag": "0.03979458",
        "sma_100": "0.03106594",
        "ema_20": "0.027694961",
        "tenkan_sen": "0.022995856",
        "rsi_divergence_bullish": "0.020015474",
        "rsi_overbought_flag": "0.018450681",
        "poc_20d": "0.017492795",
        "fib_618_level": "0.01719421",
        "kijun_sen": "0.016489845",
        "ema_10": "0.015875578",
        "open_fvg_below": "0.013682569",
        "fib_ext_1272": "0.013599905",
        "sma_20": "0.013589831",
        "fib_786_level": "0.012685932",
        "inside_resistance_zone": "0.012663755",
        "ma_score_stock": "0.012456552",
        "fib_ext_1618": "0.011950851",
        "sma_5": "0.011662818",
        "senkou_span_b": "0.011646273",
        "sar_flip_bearish": "0.011508795"
      }
    },
    "SAR_MACD": {
      "target": "fwd_positive_t20",
      "accuracy": 0.566,
      "auc": 0.6011,
      "top_features": {
        "sma_100": "0.05516063",
        "ema_20": "0.053428285",
        "fib_618_level": "0.048937846",
        "fib_382_level": "0.037072644",
        "ema_100": "0.029126128",
        "alligator_lips": "0.025058117",
        "senkou_span_a": "0.01880345",
        "open_fvg_below": "0.01841331",
        "sma_5": "0.018313171",
        "nearest_support": "0.017775169",
        "fib_786_level": "0.017355092",
        "macd_line": "0.014885328",
        "fib_ext_1618": "0.014805672",
        "dmi_bullish_flag": "0.014518844",
        "chikou_span": "0.014427728",
        "ema_200": "0.0140530765",
        "uptrend_health": "0.013696078",
        "dist_sma_200": "0.013497565",
        "fib_ext_1272": "0.013132336",
        "bb_upper": "0.0118402345"
      }
    },
    "BOLLINGER": {
      "target": "fwd_positive_t5",
      "accuracy": 0.5304,
      "auc": 0.5513,
      "top_features": {
        "vol_explosion_streak": "0.03424502",
        "sma_100": "0.019730475",
        "fib_786_level": "0.019343905",
        "price_below_cloud": "0.018383428",
        "bos_bullish": "0.017430926",
        "price_above_cloud": "0.01671771",
        "ema_10": "0.016446149",
        "rsi_divergence_bearish": "0.015136562",
        "hit_ceiling": "0.014655505",
        "sma_5": "0.013862016",
        "swing_high_252": "0.013782987",
        "dmi_crossover_bullish": "0.013582139",
        "decline_20d_flag": "0.013562363",
        "rsi_divergence_bullish": "0.01333579",
        "fib_ext_1618": "0.012680294",
        "tenkan_sen": "0.01218742",
        "fib_618_level": "0.011513983",
        "fib_382_level": "0.010935394",
        "uptrend_duration": "0.010333726",
        "open_fvg_below": "0.009950911"
      }
    },
    "VOLUME_EXPLOSION": {
      "target": "fwd_positive_t180",
      "accuracy": 0.5199,
      "auc": 0.7514,
      "top_features": {
        "nearest_support": "0.2715468",
        "bb_lower": "0.12468492",
        "vol_60d": "0.041218378",
        "fib_786_level": "0.03440862",
        "swing_high_252": "0.02830662",
        "ema_100": "0.027643206",
        "sma_200": "0.025250593",
        "adv_20": "0.024644932",
        "sma_100": "0.021356927",
        "ema_10": "0.018843258",
        "ema_5": "0.01779399",
        "senkou_span_b": "0.016852846",
        "stoch_rsi_oversold": "0.01651026",
        "sma_10": "0.016448325",
        "sma_50": "0.013607877",
        "swing_low_252": "0.012662029",
        "ema_50": "0.012656012",
        "open_fvg_above": "0.012206344",
        "atr_14": "0.011871646",
        "ema_200": "0.010363258"
      }
    },
    "UPTREND": {
      "target": "fwd_positive_t180",
      "accuracy": 0.5199,
      "auc": 0.7514,
      "top_features": {
        "nearest_support": "0.2715468",
        "bb_lower": "0.12468492",
        "vol_60d": "0.041218378",
        "fib_786_level": "0.03440862",
        "swing_high_252": "0.02830662",
        "ema_100": "0.027643206",
        "sma_200": "0.025250593",
        "adv_20": "0.024644932",
        "sma_100": "0.021356927",
        "ema_10": "0.018843258",
        "ema_5": "0.01779399",
        "senkou_span_b": "0.016852846",
        "stoch_rsi_oversold": "0.01651026",
        "sma_10": "0.016448325",
        "sma_50": "0.013607877",
        "swing_low_252": "0.012662029",
        "ema_50": "0.012656012",
        "open_fvg_above": "0.012206344",
        "atr_14": "0.011871646",
        "ema_200": "0.010363258"
      }
    },
    "STOCH_RSI": {
      "target": "fwd_positive_t180",
      "accuracy": 0.5199,
      "auc": 0.7514,
      "top_features": {
        "nearest_support": "0.2715468",
        "bb_lower": "0.12468492",
        "vol_60d": "0.041218378",
        "fib_786_level": "0.03440862",
        "swing_high_252": "0.02830662",
        "ema_100": "0.027643206",
        "sma_200": "0.025250593",
        "adv_20": "0.024644932",
        "sma_100": "0.021356927",
        "ema_10": "0.018843258",
        "ema_5": "0.01779399",
        "senkou_span_b": "0.016852846",
        "stoch_rsi_oversold": "0.01651026",
        "sma_10": "0.016448325",
        "sma_50": "0.013607877",
        "swing_low_252": "0.012662029",
        "ema_50": "0.012656012",
        "open_fvg_above": "0.012206344",
        "atr_14": "0.011871646",
        "ema_200": "0.010363258"
      }
    },
    "GENERAL": {
      "target": "fwd_positive_t20",
      "accuracy": 0.566,
      "auc": 0.6011,
      "top_features": {
        "sma_100": "0.05516063",
        "ema_20": "0.053428285",
        "fib_618_level": "0.048937846",
        "fib_382_level": "0.037072644",
        "ema_100": "0.029126128",
        "alligator_lips": "0.025058117",
        "senkou_span_a": "0.01880345",
        "open_fvg_below": "0.01841331",
        "sma_5": "0.018313171",
        "nearest_support": "0.017775169",
        "fib_786_level": "0.017355092",
        "macd_line": "0.014885328",
        "fib_ext_1618": "0.014805672",
        "dmi_bullish_flag": "0.014518844",
        "chikou_span": "0.014427728",
        "ema_200": "0.0140530765",
        "uptrend_health": "0.013696078",
        "dist_sma_200": "0.013497565",
        "fib_ext_1272": "0.013132336",
        "bb_upper": "0.0118402345"
      }
    }
  }
}