{
  "ticker": "KBC",
  "models": {
    "PRICE_DOWN_15_MA20": {
      "target": "fwd_positive_t180",
      "accuracy": 0.6817,
      "auc": 0.8398,
      "top_features": {
        "swing_low_252": "0.06493268",
        "sma_10": "0.06172822",
        "atr_14": "0.054582983",
        "dist_to_52w_low_pct": "0.04413358",
        "ema_20": "0.043867238",
        "sma_20": "0.043359753",
        "alligator_jaw": "0.040171426",
        "dist_to_52w_high_pct": "0.032535408",
        "ema_100": "0.031535756",
        "ema_50": "0.028477153",
        "ma_score_stock": "0.028441794",
        "fib_618_level": "0.026304312",
        "vol_60d": "0.024647422",
        "ema_200": "0.019535052",
        "dist_sma_200": "0.0155816935",
        "sma_5": "0.01542132",
        "vnindex_ma_score": "0.014703882",
        "cci_20": "0.013879264",
        "sma_200": "0.013769393",
        "bb_mid": "0.013391127"
      }
    },
    "RSI_OVERSOLD": {
      "target": "fwd_positive_t60",
      "accuracy": 0.7926,
      "auc": 0.8686,
      "top_features": {
        "fib_ext_1272": "0.040812906",
        "swing_low_252": "0.031151272",
        "sma_200": "0.031046579",
        "tenkan_sen": "0.026719775",
        "kijun_sen": "0.026058922",
        "dist_to_52w_high_pct": "0.025396522",
        "adv_20": "0.02329653",
        "cloud_bullish": "0.022658974",
        "poc_20d": "0.021874296",
        "ema_200": "0.021569092",
        "sma_50": "0.02020983",
        "dist_sma_200": "0.018376198",
        "senkou_span_b": "0.018169837",
        "ema_100": "0.017216908",
        "bb_lower": "0.016971663",
        "senkou_span_a": "0.016498549",
        "swing_high_252": "0.016323568",
        "breadth_pct_above_50sma": "0.014872052",
        "atr_14": "0.014418294",
        "vol_60d": "0.014171564"
      }
    },
    "PRICE_DOWN_15_20D": {
      "target": "fwd_positive_t5",
      "accuracy": 0.5441,
      "auc": 0.5653,
      "top_features": {
        "swing_low_252": "0.016267145",
        "dmi_crossover_bullish": "0.015787357",
        "three_pushes_high_flag": "0.0149421105",
        "ema_5": "0.0139631545",
        "ema_200": "0.01272359",
        "fib_ext_1618": "0.0124223875",
        "swing_high_252": "0.0114683425",
        "dmi_bullish_flag": "0.011372675",
        "chikou_span": "0.010952917",
        "bull_power": "0.010854505",
        "sma_10": "0.010694896",
        "senkou_span_b": "0.010651076",
        "ema_10": "0.010494075",
        "adx_14": "0.010484825",
        "tenkan_sen": "0.010363265",
        "deep_oversold_ma20_flag": "0.010351865",
        "aroon_oscillator": "0.010268298",
        "breadth_pct_above_50sma": "0.010100159",
        "earnings_season_flag": "0.010074923",
        "fib_ext_1272": "0.01006282"
      }
    },
    "DMI_WAVE": {
      "target": "fwd_positive_t10",
      "accuracy": 0.6509,
      "auc": 0.7054,
      "top_features": {
        "kijun_sen": "0.017738027",
        "swing_low_252": "0.017054591",
        "chikou_span": "0.01603711",
        "fib_ext_1618": "0.015911845",
        "at_fib_382_flag": "0.015017171",
        "sma_50": "0.014549044",
        "earnings_season_flag": "0.014320307",
        "fib_ext_1272": "0.0138311945",
        "sar_bullish": "0.013743123",
        "ema_5": "0.013670646",
        "fib_786_level": "0.013649231",
        "senkou_span_a": "0.0136195365",
        "rsi_14": "0.013591553",
        "fib_618_level": "0.013362741",
        "vol_20d": "0.012664094",
        "uptrend_quality_score": "0.012595286",
        "ema_10": "0.012338334",
        "sma_10": "0.012317722",
        "dist_to_52w_low_pct": "0.012316753",
        "poc_20d": "0.012104221"
      }
    },
    "SAR_MACD": {
      "target": "fwd_positive_t20",
      "accuracy": 0.7351,
      "auc": 0.8117,
      "top_features": {
        "dmi_bullish_flag": "0.034492586",
        "inside_resistance_zone": "0.025872117",
        "ema_5": "0.025747985",
        "ema_20": "0.024043724",
        "kijun_sen": "0.022760285",
        "fib_ext_1618": "0.022677328",
        "adv_20": "0.021112377",
        "ema_10": "0.020004356",
        "ema_200": "0.018570354",
        "chikou_span": "0.018183665",
        "poc_20d": "0.017889546",
        "dist_to_52w_high_pct": "0.016691174",
        "sma_200": "0.01653303",
        "fib_ext_1272": "0.01646683",
        "bb_squeeze_flag": "0.015635135",
        "bb_mid": "0.013664346",
        "bb_pct_b": "0.013410451",
        "sma_100": "0.0131698735",
        "dist_sma_200": "0.012926124",
        "vol_20d": "0.012881514"
      }
    },
    "BOLLINGER": {
      "target": "fwd_positive_t5",
      "accuracy": 0.5441,
      "auc": 0.5653,
      "top_features": {
        "swing_low_252": "0.016267145",
        "dmi_crossover_bullish": "0.015787357",
        "three_pushes_high_flag": "0.0149421105",
        "ema_5": "0.0139631545",
        "ema_200": "0.01272359",
        "fib_ext_1618": "0.0124223875",
        "swing_high_252": "0.0114683425",
        "dmi_bullish_flag": "0.011372675",
        "chikou_span": "0.010952917",
        "bull_power": "0.010854505",
        "sma_10": "0.010694896",
        "senkou_span_b": "0.010651076",
        "ema_10": "0.010494075",
        "adx_14": "0.010484825",
        "tenkan_sen": "0.010363265",
        "deep_oversold_ma20_flag": "0.010351865",
        "aroon_oscillator": "0.010268298",
        "breadth_pct_above_50sma": "0.010100159",
        "earnings_season_flag": "0.010074923",
        "fib_ext_1272": "0.01006282"
      }
    },
    "VOLUME_EXPLOSION": {
      "target": "fwd_positive_t180",
      "accuracy": 0.6817,
      "auc": 0.8398,
      "top_features": {
        "swing_low_252": "0.06493268",
        "sma_10": "0.06172822",
        "atr_14": "0.054582983",
        "dist_to_52w_low_pct": "0.04413358",
        "ema_20": "0.043867238",
        "sma_20": "0.043359753",
        "alligator_jaw": "0.040171426",
        "dist_to_52w_high_pct": "0.032535408",
        "ema_100": "0.031535756",
        "ema_50": "0.028477153",
        "ma_score_stock": "0.028441794",
        "fib_618_level": "0.026304312",
        "vol_60d": "0.024647422",
        "ema_200": "0.019535052",
        "dist_sma_200": "0.0155816935",
        "sma_5": "0.01542132",
        "vnindex_ma_score": "0.014703882",
        "cci_20": "0.013879264",
        "sma_200": "0.013769393",
        "bb_mid": "0.013391127"
      }
    },
    "UPTREND": {
      "target": "fwd_positive_t180",
      "accuracy": 0.6817,
      "auc": 0.8398,
      "top_features": {
        "swing_low_252": "0.06493268",
        "sma_10": "0.06172822",
        "atr_14": "0.054582983",
        "dist_to_52w_low_pct": "0.04413358",
        "ema_20": "0.043867238",
        "sma_20": "0.043359753",
        "alligator_jaw": "0.040171426",
        "dist_to_52w_high_pct": "0.032535408",
        "ema_100": "0.031535756",
        "ema_50": "0.028477153",
        "ma_score_stock": "0.028441794",
        "fib_618_level": "0.026304312",
        "vol_60d": "0.024647422",
        "ema_200": "0.019535052",
        "dist_sma_200": "0.0155816935",
        "sma_5": "0.01542132",
        "vnindex_ma_score": "0.014703882",
        "cci_20": "0.013879264",
        "sma_200": "0.013769393",
        "bb_mid": "0.013391127"
      }
    },
    "STOCH_RSI": {
      "target": "fwd_positive_t180",
      "accuracy": 0.6817,
      "auc": 0.8398,
      "top_features": {
        "swing_low_252": "0.06493268",
        "sma_10": "0.06172822",
        "atr_14": "0.054582983",
        "dist_to_52w_low_pct": "0.04413358",
        "ema_20": "0.043867238",
        "sma_20": "0.043359753",
        "alligator_jaw": "0.040171426",
        "dist_to_52w_high_pct": "0.032535408",
        "ema_100": "0.031535756",
        "ema_50": "0.028477153",
        "ma_score_stock": "0.028441794",
        "fib_618_level": "0.026304312",
        "vol_60d": "0.024647422",
        "ema_200": "0.019535052",
        "dist_sma_200": "0.0155816935",
        "sma_5": "0.01542132",
        "vnindex_ma_score": "0.014703882",
        "cci_20": "0.013879264",
        "sma_200": "0.013769393",
        "bb_mid": "0.013391127"
      }
    },
    "GENERAL": {
      "target": "fwd_positive_t20",
      "accuracy": 0.7351,
      "auc": 0.8117,
      "top_features": {
        "dmi_bullish_flag": "0.034492586",
        "inside_resistance_zone": "0.025872117",
        "ema_5": "0.025747985",
        "ema_20": "0.024043724",
        "kijun_sen": "0.022760285",
        "fib_ext_1618": "0.022677328",
        "adv_20": "0.021112377",
        "ema_10": "0.020004356",
        "ema_200": "0.018570354",
        "chikou_span": "0.018183665",
        "poc_20d": "0.017889546",
        "dist_to_52w_high_pct": "0.016691174",
        "sma_200": "0.01653303",
        "fib_ext_1272": "0.01646683",
        "bb_squeeze_flag": "0.015635135",
        "bb_mid": "0.013664346",
        "bb_pct_b": "0.013410451",
        "sma_100": "0.0131698735",
        "dist_sma_200": "0.012926124",
        "vol_20d": "0.012881514"
      }
    }
  }
}