{
  "ticker": "LPB",
  "models": {
    "PRICE_DOWN_15_MA20": {
      "target": "fwd_positive_t180",
      "accuracy": 0.7083,
      "auc": 0.6991,
      "top_features": {
        "price_above_cloud": "0.21599859",
        "ema_200": "0.1301779",
        "swing_low_252": "0.05962768",
        "dist_to_52w_high_pct": "0.05452958",
        "dist_to_52w_low_pct": "0.053857103",
        "sma_100": "0.034718942",
        "vol_20d": "0.03318107",
        "ema_100": "0.031678997",
        "return_60d": "0.02866457",
        "sma_5": "0.027848752",
        "sma_200": "0.02310029",
        "senkou_span_b": "0.022623451",
        "dist_sma_200": "0.02078178",
        "plus_di_14": "0.015342261",
        "swing_high_252": "0.015113156",
        "uptrend_health": "0.014141654",
        "sma_20": "0.012855313",
        "ema_10": "0.011981846",
        "uptrend_quality_score": "0.010720171",
        "bb_width": "0.010487857"
      }
    },
    "RSI_OVERSOLD": {
      "target": "fwd_positive_t60",
      "accuracy": 0.6016,
      "auc": 0.8306,
      "top_features": {
        "uptrend_duration": "0.12160585",
        "kijun_sen": "0.04903146",
        "garch_sigma": "0.03559189",
        "dist_to_52w_high_pct": "0.031029597",
        "fib_ext_1272": "0.0281108",
        "open_fvg_above": "0.027468484",
        "sma_5": "0.023963988",
        "ema_50": "0.022363301",
        "fib_618_level": "0.020794345",
        "dist_sma_200": "0.020574274",
        "hurst_60d": "0.018280467",
        "sma_200": "0.017354444",
        "rsi_divergence_bearish": "0.016909828",
        "t25_risk": "0.016636569",
        "dist_to_52w_low_pct": "0.016367288",
        "bb_expansion_flag": "0.016309958",
        "bb_pct_b": "0.015008862",
        "ema_200": "0.014989454",
        "pullback_volume_dryup": "0.014300339",
        "senkou_span_b": "0.014231411"
      }
    },
    "PRICE_DOWN_15_20D": {
      "target": "fwd_positive_t5",
      "accuracy": 0.5286,
      "auc": 0.5585,
      "top_features": {
        "vol_explosion_direction": "0.043029882",
        "bb_squeeze_flag": "0.037474036",
        "market_structure_bullish": "0.029654672",
        "rsi_divergence_bearish": "0.028263675",
        "open_fvg_below": "0.02631688",
        "bb_expansion_flag": "0.025442708",
        "at_fib_382_flag": "0.02440515",
        "shooting_star_at_resistance": "0.023573063",
        "bb_breakout_direction": "0.023493735",
        "ema_50": "0.02296864",
        "fib_confluence_flag": "0.022496132",
        "rsi_divergence_bullish": "0.020965444",
        "open_fvg_above": "0.02066301",
        "falling_wedge_flag": "0.0185356",
        "ema_20": "0.017109528",
        "fib_382_level": "0.01666856",
        "sma_10": "0.016477106",
        "hurst_60d": "0.015793469",
        "fib_ext_1272": "0.013446911",
        "earnings_season_flag": "0.013231688"
      }
    },
    "DMI_WAVE": {
      "target": "fwd_positive_t10",
      "accuracy": 0.6016,
      "auc": 0.5785,
      "top_features": {
        "stoch_rsi_overbought": "0.07578212",
        "earnings_season_flag": "0.051610626",
        "fib_786_level": "0.033908594",
        "fib_ext_1272": "0.02943591",
        "rsi_divergence_bearish": "0.027450258",
        "hit_ceiling": "0.026911533",
        "bb_squeeze_flag": "0.025259448",
        "fib_618_level": "0.021568747",
        "inside_support_zone": "0.020934572",
        "open_fvg_below": "0.020343471",
        "uptrend_duration": "0.017365467",
        "cci_bullish_divergence": "0.016749114",
        "hurst_60d": "0.016363816",
        "fib_382_level": "0.015951496",
        "fvg_bearish": "0.015749915",
        "fvg_bullish": "0.01493317",
        "swing_high_252": "0.014469798",
        "chikou_span": "0.011641803",
        "ema_10": "0.011537352",
        "senkou_span_a": "0.01126634"
      }
    },
    "SAR_MACD": {
      "target": "fwd_positive_t20",
      "accuracy": 0.599,
      "auc": 0.4694,
      "top_features": {
        "bb_breakout_direction": "0.07473572",
        "bos_bullish": "0.042602167",
        "ema_10": "0.039002504",
        "uptrend_duration": "0.03598145",
        "open_fvg_above": "0.032861505",
        "earnings_season_flag": "0.03225352",
        "bb_expansion_flag": "0.031754732",
        "fib_618_level": "0.03013811",
        "fib_786_level": "0.027276462",
        "ema_5": "0.02438309",
        "bb_squeeze_flag": "0.02420519",
        "open_fvg_below": "0.016462315",
        "senkou_span_b": "0.015453404",
        "sma_10": "0.014234968",
        "nearest_support": "0.01392236",
        "adv_dec_ratio_10d": "0.013908701",
        "chikou_span": "0.013883199",
        "vol_60d": "0.013829132",
        "sma_5": "0.01338849",
        "bb_mid": "0.013259526"
      }
    },
    "BOLLINGER": {
      "target": "fwd_positive_t5",
      "accuracy": 0.5286,
      "auc": 0.5585,
      "top_features": {
        "vol_explosion_direction": "0.043029882",
        "bb_squeeze_flag": "0.037474036",
        "market_structure_bullish": "0.029654672",
        "rsi_divergence_bearish": "0.028263675",
        "open_fvg_below": "0.02631688",
        "bb_expansion_flag": "0.025442708",
        "at_fib_382_flag": "0.02440515",
        "shooting_star_at_resistance": "0.023573063",
        "bb_breakout_direction": "0.023493735",
        "ema_50": "0.02296864",
        "fib_confluence_flag": "0.022496132",
        "rsi_divergence_bullish": "0.020965444",
        "open_fvg_above": "0.02066301",
        "falling_wedge_flag": "0.0185356",
        "ema_20": "0.017109528",
        "fib_382_level": "0.01666856",
        "sma_10": "0.016477106",
        "hurst_60d": "0.015793469",
        "fib_ext_1272": "0.013446911",
        "earnings_season_flag": "0.013231688"
      }
    },
    "VOLUME_EXPLOSION": {
      "target": "fwd_positive_t180",
      "accuracy": 0.7083,
      "auc": 0.6991,
      "top_features": {
        "price_above_cloud": "0.21599859",
        "ema_200": "0.1301779",
        "swing_low_252": "0.05962768",
        "dist_to_52w_high_pct": "0.05452958",
        "dist_to_52w_low_pct": "0.053857103",
        "sma_100": "0.034718942",
        "vol_20d": "0.03318107",
        "ema_100": "0.031678997",
        "return_60d": "0.02866457",
        "sma_5": "0.027848752",
        "sma_200": "0.02310029",
        "senkou_span_b": "0.022623451",
        "dist_sma_200": "0.02078178",
        "plus_di_14": "0.015342261",
        "swing_high_252": "0.015113156",
        "uptrend_health": "0.014141654",
        "sma_20": "0.012855313",
        "ema_10": "0.011981846",
        "uptrend_quality_score": "0.010720171",
        "bb_width": "0.010487857"
      }
    },
    "UPTREND": {
      "target": "fwd_positive_t180",
      "accuracy": 0.7083,
      "auc": 0.6991,
      "top_features": {
        "price_above_cloud": "0.21599859",
        "ema_200": "0.1301779",
        "swing_low_252": "0.05962768",
        "dist_to_52w_high_pct": "0.05452958",
        "dist_to_52w_low_pct": "0.053857103",
        "sma_100": "0.034718942",
        "vol_20d": "0.03318107",
        "ema_100": "0.031678997",
        "return_60d": "0.02866457",
        "sma_5": "0.027848752",
        "sma_200": "0.02310029",
        "senkou_span_b": "0.022623451",
        "dist_sma_200": "0.02078178",
        "plus_di_14": "0.015342261",
        "swing_high_252": "0.015113156",
        "uptrend_health": "0.014141654",
        "sma_20": "0.012855313",
        "ema_10": "0.011981846",
        "uptrend_quality_score": "0.010720171",
        "bb_width": "0.010487857"
      }
    },
    "STOCH_RSI": {
      "target": "fwd_positive_t180",
      "accuracy": 0.7083,
      "auc": 0.6991,
      "top_features": {
        "price_above_cloud": "0.21599859",
        "ema_200": "0.1301779",
        "swing_low_252": "0.05962768",
        "dist_to_52w_high_pct": "0.05452958",
        "dist_to_52w_low_pct": "0.053857103",
        "sma_100": "0.034718942",
        "vol_20d": "0.03318107",
        "ema_100": "0.031678997",
        "return_60d": "0.02866457",
        "sma_5": "0.027848752",
        "sma_200": "0.02310029",
        "senkou_span_b": "0.022623451",
        "dist_sma_200": "0.02078178",
        "plus_di_14": "0.015342261",
        "swing_high_252": "0.015113156",
        "uptrend_health": "0.014141654",
        "sma_20": "0.012855313",
        "ema_10": "0.011981846",
        "uptrend_quality_score": "0.010720171",
        "bb_width": "0.010487857"
      }
    },
    "GENERAL": {
      "target": "fwd_positive_t20",
      "accuracy": 0.599,
      "auc": 0.4694,
      "top_features": {
        "bb_breakout_direction": "0.07473572",
        "bos_bullish": "0.042602167",
        "ema_10": "0.039002504",
        "uptrend_duration": "0.03598145",
        "open_fvg_above": "0.032861505",
        "earnings_season_flag": "0.03225352",
        "bb_expansion_flag": "0.031754732",
        "fib_618_level": "0.03013811",
        "fib_786_level": "0.027276462",
        "ema_5": "0.02438309",
        "bb_squeeze_flag": "0.02420519",
        "open_fvg_below": "0.016462315",
        "senkou_span_b": "0.015453404",
        "sma_10": "0.014234968",
        "nearest_support": "0.01392236",
        "adv_dec_ratio_10d": "0.013908701",
        "chikou_span": "0.013883199",
        "vol_60d": "0.013829132",
        "sma_5": "0.01338849",
        "bb_mid": "0.013259526"
      }
    }
  }
}