{
  "ticker": "VPB",
  "models": {
    "PRICE_DOWN_15_MA20": {
      "target": "fwd_positive_t180",
      "accuracy": 0.6071,
      "auc": 0.8747,
      "top_features": {
        "poc_20d": "0.17604007",
        "ema_10": "0.06092498",
        "nearest_resistance": "0.052502997",
        "ema_20": "0.039255723",
        "sma_20": "0.028062344",
        "swing_low_252": "0.027190525",
        "fib_ext_1272": "0.026862748",
        "ema_5": "0.021796558",
        "sma_5": "0.018650973",
        "sma_10": "0.018441899",
        "nearest_support": "0.017600605",
        "uptrend_quality_score": "0.017217305",
        "adv_20": "0.015220787",
        "kijun_sen": "0.014842841",
        "breadth_pct_above_50sma": "0.014053085",
        "sma_200": "0.013300338",
        "fib_ext_1618": "0.013124139",
        "bb_mid": "0.012759164",
        "ema_100": "0.012450324",
        "tenkan_sen": "0.012343209"
      }
    },
    "RSI_OVERSOLD": {
      "target": "fwd_positive_t60",
      "accuracy": 0.7245,
      "auc": 0.6307,
      "top_features": {
        "cloud_bullish": "0.051864102",
        "swing_low_252": "0.03136363",
        "ema_5": "0.026506322",
        "fib_382_level": "0.02470027",
        "vol_60d": "0.024394048",
        "price_above_cloud": "0.022762075",
        "senkou_span_a": "0.02049516",
        "sma_100": "0.01947453",
        "sma_50": "0.019029308",
        "dist_sma_50": "0.018872801",
        "swing_high_252": "0.017248128",
        "adv_20": "0.016858263",
        "plus_di_14": "0.016211402",
        "garch_sigma": "0.016119793",
        "ema_20": "0.015650908",
        "macd_signal": "0.014941157",
        "dist_to_52w_high_pct": "0.014098204",
        "alligator_jaw": "0.01405576",
        "ema_100": "0.013890666",
        "dist_sma_200": "0.013819222"
      }
    },
    "PRICE_DOWN_15_20D": {
      "target": "fwd_positive_t5",
      "accuracy": 0.5051,
      "auc": 0.5345,
      "top_features": {
        "price_above_cloud": "0.056235876",
        "alligator_lips": "0.01476837",
        "fib_382_level": "0.014610371",
        "ema_100": "0.0135899745",
        "swing_low_252": "0.013458009",
        "cloud_bullish": "0.013263079",
        "chikou_span": "0.01303264",
        "kijun_sen": "0.012940381",
        "nearest_resistance": "0.012887414",
        "sma_100": "0.012276864",
        "senkou_span_b": "0.012178756",
        "sar_bullish": "0.01213337",
        "ema_200": "0.011604498",
        "sma_50": "0.011576584",
        "earnings_season_flag": "0.010583059",
        "ema_10": "0.010552571",
        "stock_rs_20d": "0.010346272",
        "sma_5": "0.010344017",
        "poc_20d": "0.0100699905",
        "nearest_support_pct": "0.009879233"
      }
    },
    "DMI_WAVE": {
      "target": "fwd_positive_t10",
      "accuracy": 0.5306,
      "auc": 0.6185,
      "top_features": {
        "ema_5": "0.03521666",
        "fib_786_level": "0.02968523",
        "rsi_divergence_bearish": "0.022950837",
        "swing_high_252": "0.01909463",
        "nearest_resistance": "0.016860334",
        "fib_ext_1272": "0.016513811",
        "sma_10": "0.015632559",
        "chikou_span": "0.015497098",
        "tenkan_sen": "0.015470609",
        "fib_618_level": "0.0153842075",
        "ema_10": "0.014625738",
        "sma_5": "0.013542748",
        "sma_100": "0.013270738",
        "fib_382_level": "0.013208978",
        "bb_upper": "0.012715661",
        "ema_50": "0.01210283",
        "swing_low_252": "0.0120533705",
        "hurst_60d": "0.011991138",
        "return_10d": "0.011591577",
        "sma_50": "0.011534122"
      }
    },
    "SAR_MACD": {
      "target": "fwd_positive_t20",
      "accuracy": 0.625,
      "auc": 0.7662,
      "top_features": {
        "fib_ext_1618": "0.03580211",
        "bb_upper": "0.026111063",
        "swing_high_252": "0.025269527",
        "ema_5": "0.023971181",
        "ema_10": "0.021925274",
        "sma_10": "0.021594685",
        "alligator_lips": "0.021290107",
        "chikou_span": "0.01991538",
        "fib_ext_1272": "0.018912869",
        "poc_20d": "0.01886607",
        "fib_618_level": "0.018586101",
        "alligator_teeth": "0.01831597",
        "bb_lower": "0.017258389",
        "sma_5": "0.0169435",
        "fib_786_level": "0.016685111",
        "swing_low_252": "0.016681032",
        "bb_mid": "0.014293451",
        "bb_pct_b": "0.012563351",
        "vol_60d": "0.012246992",
        "adv_20": "0.012167923"
      }
    },
    "BOLLINGER": {
      "target": "fwd_positive_t5",
      "accuracy": 0.5051,
      "auc": 0.5345,
      "top_features": {
        "price_above_cloud": "0.056235876",
        "alligator_lips": "0.01476837",
        "fib_382_level": "0.014610371",
        "ema_100": "0.0135899745",
        "swing_low_252": "0.013458009",
        "cloud_bullish": "0.013263079",
        "chikou_span": "0.01303264",
        "kijun_sen": "0.012940381",
        "nearest_resistance": "0.012887414",
        "sma_100": "0.012276864",
        "senkou_span_b": "0.012178756",
        "sar_bullish": "0.01213337",
        "ema_200": "0.011604498",
        "sma_50": "0.011576584",
        "earnings_season_flag": "0.010583059",
        "ema_10": "0.010552571",
        "stock_rs_20d": "0.010346272",
        "sma_5": "0.010344017",
        "poc_20d": "0.0100699905",
        "nearest_support_pct": "0.009879233"
      }
    },
    "VOLUME_EXPLOSION": {
      "target": "fwd_positive_t180",
      "accuracy": 0.6071,
      "auc": 0.8747,
      "top_features": {
        "poc_20d": "0.17604007",
        "ema_10": "0.06092498",
        "nearest_resistance": "0.052502997",
        "ema_20": "0.039255723",
        "sma_20": "0.028062344",
        "swing_low_252": "0.027190525",
        "fib_ext_1272": "0.026862748",
        "ema_5": "0.021796558",
        "sma_5": "0.018650973",
        "sma_10": "0.018441899",
        "nearest_support": "0.017600605",
        "uptrend_quality_score": "0.017217305",
        "adv_20": "0.015220787",
        "kijun_sen": "0.014842841",
        "breadth_pct_above_50sma": "0.014053085",
        "sma_200": "0.013300338",
        "fib_ext_1618": "0.013124139",
        "bb_mid": "0.012759164",
        "ema_100": "0.012450324",
        "tenkan_sen": "0.012343209"
      }
    },
    "UPTREND": {
      "target": "fwd_positive_t180",
      "accuracy": 0.6071,
      "auc": 0.8747,
      "top_features": {
        "poc_20d": "0.17604007",
        "ema_10": "0.06092498",
        "nearest_resistance": "0.052502997",
        "ema_20": "0.039255723",
        "sma_20": "0.028062344",
        "swing_low_252": "0.027190525",
        "fib_ext_1272": "0.026862748",
        "ema_5": "0.021796558",
        "sma_5": "0.018650973",
        "sma_10": "0.018441899",
        "nearest_support": "0.017600605",
        "uptrend_quality_score": "0.017217305",
        "adv_20": "0.015220787",
        "kijun_sen": "0.014842841",
        "breadth_pct_above_50sma": "0.014053085",
        "sma_200": "0.013300338",
        "fib_ext_1618": "0.013124139",
        "bb_mid": "0.012759164",
        "ema_100": "0.012450324",
        "tenkan_sen": "0.012343209"
      }
    },
    "STOCH_RSI": {
      "target": "fwd_positive_t180",
      "accuracy": 0.6071,
      "auc": 0.8747,
      "top_features": {
        "poc_20d": "0.17604007",
        "ema_10": "0.06092498",
        "nearest_resistance": "0.052502997",
        "ema_20": "0.039255723",
        "sma_20": "0.028062344",
        "swing_low_252": "0.027190525",
        "fib_ext_1272": "0.026862748",
        "ema_5": "0.021796558",
        "sma_5": "0.018650973",
        "sma_10": "0.018441899",
        "nearest_support": "0.017600605",
        "uptrend_quality_score": "0.017217305",
        "adv_20": "0.015220787",
        "kijun_sen": "0.014842841",
        "breadth_pct_above_50sma": "0.014053085",
        "sma_200": "0.013300338",
        "fib_ext_1618": "0.013124139",
        "bb_mid": "0.012759164",
        "ema_100": "0.012450324",
        "tenkan_sen": "0.012343209"
      }
    },
    "GENERAL": {
      "target": "fwd_positive_t20",
      "accuracy": 0.625,
      "auc": 0.7662,
      "top_features": {
        "fib_ext_1618": "0.03580211",
        "bb_upper": "0.026111063",
        "swing_high_252": "0.025269527",
        "ema_5": "0.023971181",
        "ema_10": "0.021925274",
        "sma_10": "0.021594685",
        "alligator_lips": "0.021290107",
        "chikou_span": "0.01991538",
        "fib_ext_1272": "0.018912869",
        "poc_20d": "0.01886607",
        "fib_618_level": "0.018586101",
        "alligator_teeth": "0.01831597",
        "bb_lower": "0.017258389",
        "sma_5": "0.0169435",
        "fib_786_level": "0.016685111",
        "swing_low_252": "0.016681032",
        "bb_mid": "0.014293451",
        "bb_pct_b": "0.012563351",
        "vol_60d": "0.012246992",
        "adv_20": "0.012167923"
      }
    }
  }
}